decamelize/__init__.py
decamelize-0.1.2.dist-info/METADATA
decamelize-0.1.2.dist-info/RECORD
decamelize-0.1.2.dist-info/WHEEL
decamelize-0.1.2.dist-info/top_level.txt
