Metadata-Version: 2.1
Name: decamelize
Version: 0.1.2
Summary: 🐍  Convert a camelized string into snake_case
Home-page: https://abranhe.com
Author: Carlos Abraham
Author-email: abraham@abranhe.com
License: UNKNOWN
Project-URL: Source, https://github.com/abranhe/decamelize
Platform: UNKNOWN
Classifier: Programming Language :: Python
Classifier: Natural Language :: English
Classifier: Environment :: Plugins
Classifier: Operating System :: OS Independent
Classifier: Intended Audience :: Developers
Classifier: License :: OSI Approved :: MIT License
